iree/_runtime/__init__.py
iree/_runtime/libs.py
iree/_runtime/scripts/iree_benchmark_executable/__main__.py
iree/_runtime/scripts/iree_benchmark_module/__main__.py
iree/_runtime/scripts/iree_c_embed_data/__main__.py
iree/_runtime/scripts/iree_convert_parameters/__main__.py
iree/_runtime/scripts/iree_cpuinfo/__main__.py
iree/_runtime/scripts/iree_create_parameters/__main__.py
iree/_runtime/scripts/iree_dump_module/__main__.py
iree/_runtime/scripts/iree_dump_parameters/__main__.py
iree/_runtime/scripts/iree_flatcc_cli/__main__.py
iree/_runtime/scripts/iree_run_module/__main__.py
iree/_runtime/scripts/iree_tracy_capture/__main__.py
iree/_runtime_libs/__init__.py
iree/_runtime_libs/_runtime.cpython-39-x86_64-linux-gnu.so
iree/_runtime_libs/iree-benchmark-executable
iree/_runtime_libs/iree-benchmark-module
iree/_runtime_libs/iree-c-embed-data
iree/_runtime_libs/iree-convert-parameters
iree/_runtime_libs/iree-cpuinfo
iree/_runtime_libs/iree-create-parameters
iree/_runtime_libs/iree-dump-module
iree/_runtime_libs/iree-dump-parameters
iree/_runtime_libs/iree-flatcc-cli
iree/_runtime_libs/iree-run-module
iree/_runtime_libs/version.py
iree/_runtime_libs_tracy/__init__.py
iree/_runtime_libs_tracy/_runtime.cpython-39-x86_64-linux-gnu.so
iree/_runtime_libs_tracy/iree-benchmark-executable
iree/_runtime_libs_tracy/iree-benchmark-module
iree/_runtime_libs_tracy/iree-c-embed-data
iree/_runtime_libs_tracy/iree-convert-parameters
iree/_runtime_libs_tracy/iree-cpuinfo
iree/_runtime_libs_tracy/iree-create-parameters
iree/_runtime_libs_tracy/iree-dump-module
iree/_runtime_libs_tracy/iree-dump-parameters
iree/_runtime_libs_tracy/iree-flatcc-cli
iree/_runtime_libs_tracy/iree-run-module
iree/_runtime_libs_tracy/iree-tracy-capture
iree/_runtime_libs_tracy/version.py
iree/runtime/__init__.py
iree/runtime/_binding.py
iree/runtime/_binding.pyi
iree/runtime/_package_test.py
iree/runtime/array_interop.py
iree/runtime/benchmark.py
iree/runtime/flags.py
iree/runtime/function.py
iree/runtime/io.py
iree_base_runtime-3.8.0.dist-info/METADATA
iree_base_runtime-3.8.0.dist-info/WHEEL
iree_base_runtime-3.8.0.dist-info/entry_points.txt
iree_base_runtime-3.8.0.dist-info/top_level.txt
iree_base_runtime-3.8.0.dist-info/RECORD
