Metadata-Version: 2.4
Name: iree-base-runtime
Version: 3.8.0
Summary: IREE Python Runtime Components
Author: IREE Authors
Author-email: iree-technical-discussion@lists.lfaidata.foundation
License: Apache-2.0
Project-URL: homepage, https://iree.dev/
Project-URL: repository, https://github.com/iree-org/iree
Project-URL: documentation, https://iree.dev/reference/bindings/python/
Classifier: Development Status :: 3 - Alpha
Classifier: License :: OSI Approved :: Apache Software License
Classifier: Programming Language :: Python :: 3
Classifier: Programming Language :: Python :: 3.9
Classifier: Programming Language :: Python :: 3.10
Classifier: Programming Language :: Python :: 3.11
Classifier: Programming Language :: Python :: 3.12
Classifier: Programming Language :: Python :: 3.13
Requires-Python: >=3.9
Requires-Dist: numpy
Requires-Dist: ml_dtypes
Dynamic: author
Dynamic: author-email
Dynamic: classifier
Dynamic: description
Dynamic: description-content-type
Dynamic: license
Dynamic: project-url
Dynamic: requires-dist
Dynamic: requires-python
Dynamic: summary
